zzload/__init__.py
zzload-1.0.2.dist-info/METADATA
zzload-1.0.2.dist-info/WHEEL
zzload-1.0.2.dist-info/top_level.txt
zzload-1.0.2.dist-info/RECORD
