Metadata-Version: 2.1
Name: zzload
Version: 1.0.2
Summary: zhizhenOs Software Generation Library
Home-page: UNKNOWN
Author: Yuanxun Technology
Author-email: yuanxunkj@qq.com
License: UNKNOWN
Platform: UNKNOWN
